CHANGELOG.txt
LICENCE.txt
MANIFEST.in
README.txt
setup.py
lib4d/__init__.py
lib4d.egg-info/PKG-INFO
lib4d.egg-info/SOURCES.txt
lib4d.egg-info/dependency_links.txt
lib4d.egg-info/top_level.txt