Metadata-Version: 2.1
Name: lib4d
Version: 0.0.1
Summary: Библиотека для работы с четырехмерной алгеброй
Home-page: UNKNOWN
Author: Aktoty
Author-email: aktoty2000@mail.ru
License: MIT
Keywords: lib4d
Platform: UNKNOWN
Classifier: Development Status :: 5 - Production/Stable
Classifier: Intended Audience :: Education
Classifier: Operating System :: Microsoft :: Windows :: Windows 10
Classifier: License :: OSI Approved :: MIT License
Classifier: Programming Language :: Python :: 3
License-File: LICENCE.txt
